sqs_message_sender/__init__.py
sqs_message_sender/sender.py
sqs_message_sender-0.3.dist-info/LICENSE
sqs_message_sender-0.3.dist-info/METADATA
sqs_message_sender-0.3.dist-info/WHEEL
sqs_message_sender-0.3.dist-info/top_level.txt
sqs_message_sender-0.3.dist-info/RECORD
